{
  "xp_values": {
    "MELEE_TO_PLAYERS": {},
    "RANGED_TO_PLAYERS": {},
    "MELEE_TO_MOBS": {},
    "DEAL_MELEE_DAMAGE": {},
    "BREW": {},
    "DEAL_RANGED_DAMAGE": {},
    "RANGED_TO_ANIMALS": {},
    "ANVIL_REPAIR": {},
    "BLOCK_PLACE": {},
    "CONSUME": {},
    "FISH": {},
    "MELEE_TO_ANIMALS": {},
    "SMELT": {},
    "ENCHANT": {},
    "RANGED_TO_MOBS": {},
    "CRAFT": {},
    "ACTIVATE_ITEM": {}
  },
  "bonuses": {
    "WORN": {},
    "HELD": {}
  },
  "requirements": {
    "USE_ENCHANTMENT": {},
    "USE": {},
    "INTERACT": {"crafting": 15},
    "BREAK": {},
    "PLACE": {"crafting": 15},
    "WEAPON": {},
    "TOOL": {},
    "WEAR": {}
  },
  "negative_effect": {},
  "override": true,
  "isTagFor": []
}