{
  "xp_values": {
    "MELEE_TO_PLAYERS": {},
    "RANGED_TO_PLAYERS": {},
    "MELEE_TO_MOBS": {},
    "DEAL_MELEE_DAMAGE": {},
    "BREW": {},
    "DEAL_RANGED_DAMAGE": {},
    "RANGED_TO_ANIMALS": {},
    "ANVIL_REPAIR": {},
    "BLOCK_PLACE": {"magic": 5, "building": 20},
    "CONSUME": {},
    "FISH": {},
    "MELEE_TO_ANIMALS": {},
    "SMELT": {},
    "ENCHANT": {},
    "RANGED_TO_MOBS": {},
    "CRAFT": {"crafting": 20},
    "ACTIVATE_ITEM": {}
  },
  "bonuses": {
    "WORN": {},
    "HELD": {}
  },
  "requirements": {
    "USE_ENCHANTMENT": {},
    "USE": {"total_level": 100},
    "INTERACT": {"total_level": 100},
    "BREAK": {},
    "PLACE": {},
    "WEAPON": {},
    "TOOL": {},
    "WEAR": {}
  },
  "negative_effect": {},
  "override": true,
  "isTagFor": ["ars_nouveau:alteration_table",
"ars_nouveau:arcane_core",
"ars_nouveau:arcane_pedestal",
"ars_nouveau:arcane_platform",
"ars_nouveau:bookwyrm_lectern",
"ars_nouveau:enchanters_eye",
"ars_nouveau:enchanting_apparatus",
"ars_nouveau:imbuement_chamber",
"ars_nouveau:potion_diffuser",
"ars_nouveau:potion_flask",
"ars_nouveau:potion_flask_amplify",
"ars_nouveau:potion_flask_extend_time",
"ars_nouveau:potion_jar",
"ars_nouveau:potion_melder",
"ars_nouveau:ritual_brazier",
"ars_nouveau:scribes_table",
"ars_nouveau:scryers_crystal",
"ars_nouveau:scryers_oculus",
"ars_nouveau:source_jar",
"ars_nouveau:spell_prism",
"ars_nouveau:void_prism"]
}